simpleLLMP/__init__.py
simpleLLMP/simpleLLMP.py
simpleLLMP-0.1.9.dist-info/LICENSE
simpleLLMP-0.1.9.dist-info/METADATA
simpleLLMP-0.1.9.dist-info/WHEEL
simpleLLMP-0.1.9.dist-info/top_level.txt
simpleLLMP-0.1.9.dist-info/RECORD
